pitchpx/__init__.py
pitchpx/mlbam.py
pitchpx/mlbam_util.py
pitchpx/setting.yml
pitchpx/baseball/__init__.py
pitchpx/baseball/retrosheet.py
pitchpx/game/__init__.py
pitchpx/game/boxscore.py
pitchpx/game/game.py
pitchpx/game/inning.py
pitchpx/game/players.py
tests/__init__.py
tests/pitchpx/__init__.py
tests/pitchpx/test_mlbam.py
tests/pitchpx/test_mlbam_util.py
tests/pitchpx/baseball/__init__.py
tests/pitchpx/baseball/test_retrosheet.py
tests/pitchpx/game/__init__.py
tests/pitchpx/game/test_boxscore.py
tests/pitchpx/game/test_game.py
tests/pitchpx/game/test_inning.py
tests/pitchpx/game/test_players.py
pitchpx-4.0.dist-info/LICENSE
pitchpx-4.0.dist-info/METADATA
pitchpx-4.0.dist-info/WHEEL
pitchpx-4.0.dist-info/entry_points.txt
pitchpx-4.0.dist-info/top_level.txt
pitchpx-4.0.dist-info/RECORD
