Metadata-Version: 2.1
Name: pitchpx
Version: 4.0
Summary: Getting Baseball data for MLBAM Gameday dataset
Home-page: https://github.com/Shinichi-Nakagawa/pitchpx
Author: Shinichi Nakagawa
Author-email: spirits.is.my.rader@gmail.com
License: MIT License
Keywords: baseball,MLB,MLBAM,SABRmetrics,SABR,Major league baseball
Platform: UNKNOWN
Classifier: Development Status :: 5 - Production/Stable
Classifier: Intended Audience :: Science/Research
Classifier: License :: OSI Approved :: MIT License
Classifier: Natural Language :: English
Classifier: Programming Language :: Python :: 3.5
Classifier: Programming Language :: Python :: 3.6
Classifier: Programming Language :: Python :: 3.7
Classifier: Programming Language :: Python :: 3 :: Only
Requires-Dist: beautifulsoup4
Requires-Dist: click
Requires-Dist: FormEncode
Requires-Dist: lxml
Requires-Dist: PyYAML
Requires-Dist: requests
